{
    "update_time": "2026-06-24 14:50:48",
    "pboc_omo": {
        "history_7d": [],
        "future_14d": []
    },
    "unlock_calendar": [],
    "exchange_rate": {
        "USDCNY_Onshore": 6.7941,
        "USDCNH_Offshore": 6.8166
    },
    "citic_futures": [],
    "macro_metrics": {
        "fear_greed": {
            "value": "-",
            "sentiment": "未知"
        },
        "commodity": {
            "gold": 880.12,
            "oil": 469.3
        },
        "interest_rate": {
            "china_lpr_5y": "nan",
            "us_bond_10y": "nan"
        },
        "margin_balance": null,
        "china_cpi": {
            "月份": "2026年05月份",
            "全国-当月": "101.2",
            "全国-同比增长": "1.2",
            "全国-环比增长": "-0.1",
            "全国-累计": "101.0",
            "城市-当月": "101.3",
            "城市-同比增长": "1.3",
            "城市-环比增长": "-0.1",
            "城市-累计": "101.0",
            "农村-当月": "101.1",
            "农村-同比增长": "1.1",
            "农村-环比增长": "-0.1",
            "农村-累计": "100.8"
        },
        "china_ppi": {
            "月份": "2026年05月份",
            "当月": "103.9",
            "当月同比增长": "3.9",
            "累计": "101.0"
        },
        "china_pmi": {
            "月份": "2026年05月份",
            "制造业-指数": "50.0",
            "制造业-同比增长": "1.01010101",
            "非制造业-指数": "50.1",
            "非制造业-同比增长": "-0.39761431"
        },
        "china_m1_m2": {
            "月份": "2026年05月份",
            "货币和准货币(M2)-数量(亿元)": "3536688.9",
            "货币和准货币(M2)-同比增长": "8.6",
            "货币和准货币(M2)-环比增长": "0.17742027",
            "货币(M1)-数量(亿元)": "1148891.41",
            "货币(M1)-同比增长": "5.5",
            "货币(M1)-环比增长": "0.26685198",
            "流通中的现金(M0)-数量(亿元)": "146854.71",
            "流通中的现金(M0)-同比增长": "11.9",
            "流通中的现金(M0)-环比增长": "-0.4222139"
        },
        "china_unemployment": null,
        "usa_cpi": {
            "商品": "美国CPI月率",
            "日期": "1970-01-01",
            "今值": "0.5",
            "预测值": "nan",
            "前值": "nan"
        },
        "usa_ppi": null,
        "usa_pmi": null,
        "usa_non_farm": {
            "商品": "美国非农就业人数",
            "日期": "1970-01-02",
            "今值": "15.3",
            "预测值": "nan",
            "前值": "-3.3"
        }
    }
}